sellermagnet_api/__init__.py
sellermagnet_api/client.py
sellermagnet_api/exceptions.py
sellermagnet_api/endpoints/__init__.py
sellermagnet_api/endpoints/amazon_deals.py
sellermagnet_api/endpoints/amazon_marketplaces.py
sellermagnet_api/endpoints/amazon_product.py
sellermagnet_api/endpoints/amazon_search.py
sellermagnet_api/endpoints/amazon_seller.py
sellermagnet_api/models/__init__.py
sellermagnet_api/models/amazon_deals.py
sellermagnet_api/models/amazon_marketplaces.py
sellermagnet_api/models/amazon_product.py
sellermagnet_api/models/amazon_search.py
sellermagnet_api/models/amazon_seller.py
sellermagnet_api-1.0.0.dist-info/licenses/LICENSE
sellermagnet_api-1.0.0.dist-info/METADATA
sellermagnet_api-1.0.0.dist-info/WHEEL
sellermagnet_api-1.0.0.dist-info/top_level.txt
sellermagnet_api-1.0.0.dist-info/RECORD
