Metadata-Version: 2.4
Name: sellermagnet-api
Version: 1.0.0
Summary: A lightweight Python client for the SellerMagnet API to access Amazon product data.
Author-email: SellerMagnetAPI <api@sellermagnet.com>
License: MIT
Project-URL: Homepage, https://sellermagnet-api.com
Project-URL: Documentation, https://sellermagnet-api.com/docs
Project-URL: Source, https://github.com/sellermagnet/sellermagnet-api
Classifier: Programming Language :: Python :: 3
Classifier: Programming Language :: Python :: 3.8
Classifier: Programming Language :: Python :: 3.9
Classifier: Programming Language :: Python :: 3.10
Classifier: Programming Language :: Python :: 3.11
Classifier: Programming Language :: Python :: 3.12
Classifier: License :: OSI Approved :: MIT License
Classifier: Operating System :: OS Independent
Classifier: Intended Audience :: Developers
Classifier: Topic :: Software Development :: Libraries :: Python Modules
Classifier: Topic :: Internet :: WWW/HTTP
Requires-Python: >=3.8
License-File: LICENSE
Requires-Dist: requests==2.32.4
Requires-Dist: tenacity==9.1.2
Dynamic: license-file
